fortunate_pkg/__init__.py
fortunate_pkg/__main__.py
fortunate_pkg/pep517_backend.py
fortunate_pkg-0.2.7.dist-info/LICENSE.md
fortunate_pkg-0.2.7.dist-info/METADATA
fortunate_pkg-0.2.7.dist-info/WHEEL
fortunate_pkg-0.2.7.dist-info/entry_points.txt
fortunate_pkg-0.2.7.dist-info/top_level.txt
fortunate_pkg-0.2.7.dist-info/RECORD
